{
	"type": "Secret",
	"descriptiveType": "Secret",
	"getDescription": "Get a secret by name",
	"listDescription": "List all secrets",
	"searchDescription": "Search for a secret using the ListOptions JSON format: https://github.com/overmindtech/k8s-source#search",
	"group": "Kubernetes",
	"terraformQuery": [
		"kubernetes_secret.metadata.name",
		"kubernetes_secret_v1.metadata.name"
	],
	"terraformMethod": "GET",
	"terraformScope": "${provider_mapping.cluster_name}.${values.metadata.namespace}",
	"links": []
}